querychat/__init__.py
querychat/_dash.py
querychat/_dash_ui.py
querychat/_datasource.py
querychat/_deprecated.py
querychat/_df_compat.py
querychat/_gradio.py
querychat/_icons.py
querychat/_querychat_base.py
querychat/_querychat_core.py
querychat/_shiny.py
querychat/_shiny_module.py
querychat/_streamlit.py
querychat/_system_prompt.py
querychat/_ui_assets.py
querychat/_utils.py
querychat/dash.py
querychat/gradio.py
querychat/shiny.py
querychat/streamlit.py
querychat/tools.py
querychat/assets/__init__.py
querychat/assets/dash/dash.css
querychat/assets/dash/dash.js
querychat/assets/gradio/gradio.css
querychat/assets/gradio/gradio.js
querychat/assets/shared/suggestion.css
querychat/assets/streamlit/streamlit.js
querychat/data/__init__.py
querychat/data/tips.csv.gz
querychat/data/titanic.csv.gz
querychat/express/__init__.py
querychat/prompts/prompt.md
querychat/prompts/tool-query.md
querychat/prompts/tool-reset-dashboard.md
querychat/prompts/tool-update-dashboard.md
querychat/static/css/styles.css
querychat/static/js/querychat.js
querychat/types/__init__.py
querychat-0.5.1.dist-info/METADATA
querychat-0.5.1.dist-info/WHEEL
querychat-0.5.1.dist-info/licenses/LICENSE.md
querychat-0.5.1.dist-info/RECORD
