Metadata-Version: 2.4
Name: querychat
Version: 0.5.1
Summary: Chat with your data using natural language
Project-URL: Homepage, https://github.com/posit-dev/querychat
Project-URL: Repository, https://github.com/posit-dev/querychat
Project-URL: Issues, https://github.com/posit-dev/querychat/issues
Project-URL: Source, https://github.com/posit-dev/querychat/tree/main/pkg-py
Author-email: Joe Cheng <joe@posit.co>, Garrick Aden-Buie <garrick@posit.co>, Carson Sievert <carson@posit.co>, Dan Chen <daniel.chen@posit.co>, Barret Schloerke <barret@posit.co>
Maintainer-email: Garrick Aden-Buie <garrick@posit.co>
License: # MIT License
License-File: LICENSE.md
Classifier: Programming Language :: Python
Classifier: Programming Language :: Python :: 3.10
Classifier: Programming Language :: Python :: 3.11
Classifier: Programming Language :: Python :: 3.12
Classifier: Programming Language :: Python :: 3.13
Classifier: Programming Language :: Python :: 3.14
Requires-Python: >=3.10
Requires-Dist: chatlas>=0.13.2
Requires-Dist: chevron
Requires-Dist: duckdb
Requires-Dist: great-tables>=0.16.0
Requires-Dist: htmltools
Requires-Dist: narwhals
Requires-Dist: shiny>=1.5.1
Requires-Dist: shinychat>=0.2.8
Requires-Dist: sqlalchemy>=2.0.0
Provides-Extra: dash
Requires-Dist: dash-ag-grid>=31.0; extra == 'dash'
Requires-Dist: dash-bootstrap-components>=2.0; extra == 'dash'
Requires-Dist: dash[async]>=3.1; extra == 'dash'
Requires-Dist: pandas; extra == 'dash'
Provides-Extra: gradio
Requires-Dist: gradio>=6.0; extra == 'gradio'
Provides-Extra: ibis
Requires-Dist: ibis-framework>=9.0.0; extra == 'ibis'
Requires-Dist: pandas; extra == 'ibis'
Provides-Extra: pandas
Requires-Dist: pandas; extra == 'pandas'
Provides-Extra: polars
Requires-Dist: polars; extra == 'polars'
Provides-Extra: streamlit
Requires-Dist: streamlit>=1.30; extra == 'streamlit'
